kipoi_utils/__init__.py
kipoi_utils/_version.py
kipoi_utils/data_utils.py
kipoi_utils/utils.py
kipoi_utils/external/__init__.py
kipoi_utils/external/flatten_json.py
kipoi_utils/external/related/__init__.py
kipoi_utils/external/related/converters.py
kipoi_utils/external/related/dispatchers.py
kipoi_utils/external/related/fields.py
kipoi_utils/external/related/mixins.py
kipoi_utils/external/torch/__init__.py
kipoi_utils/external/torch/data.py
kipoi_utils/external/torch/sampler.py
kipoi_utils/external/torchvision/__init__.py
kipoi_utils/external/torchvision/dataset_utils.py
tests/__init__.py
tests/test_013_data_utils.py
tests/test_dataset_utils.py
tests/test_utils_flatten_json.py
tests/test_utils_list_files.py
tests/test_utils_load_module.py
tests/test_utils_parse.py
tests/test_utils_recursive_parse.py
kipoi_utils-0.7.7.dist-info/LICENSE
kipoi_utils-0.7.7.dist-info/METADATA
kipoi_utils-0.7.7.dist-info/WHEEL
kipoi_utils-0.7.7.dist-info/top_level.txt
kipoi_utils-0.7.7.dist-info/RECORD
