Metadata-Version: 2.1
Name: kipoi-utils
Version: 0.7.7
Summary: kipoi-utils: utils used in various packages related to kipoi
Home-page: https://github.com/kipoi/kipoi-utils
Author: Kipoi team
Author-email: thorsten.beier@embl.de
License: MIT license
Keywords: model zoo,deep learning,computational biology,bioinformatics,genomics
License-File: LICENSE
Requires-Dist: pandas (>=0.21.0)
Requires-Dist: tqdm
Requires-Dist: attrs
Requires-Dist: related
Requires-Dist: numpy
Requires-Dist: PyYAML (>=5.1.0)
Provides-Extra: develop
Requires-Dist: bumpversion ; extra == 'develop'
Requires-Dist: wheel ; extra == 'develop'
Requires-Dist: pytest (>=3.3.1) ; extra == 'develop'
Requires-Dist: pytest-xdist ; extra == 'develop'
Requires-Dist: pytest-pep8 ; extra == 'develop'
Requires-Dist: pytest-cov ; extra == 'develop'
Requires-Dist: coveralls ; extra == 'develop'
